Adder/adder.vhdl
library ieee;
use ieee.std_logic_1164.all;

entity adder is
	-- 'i0', 'i1', and the carry-in 'ci' are inputs of the adder
	-- 's' is the sum output, 'co' is the carry-out
	port (i0, i1 : in bit; ci : in bit; s : out bit; co : out bit);
end adder;

architecture rtl of adder is
begin
	-- This full-adder architecture contains two concurrent assignments
	-- Compute the carry
	s <= i0 xor i1 xor ci;
	-- Compute the carry
	co <= (i0 and i1) or (i0 and ci) or (i1 and ci);
end rtl;

Adder/adder_tb.vhdl
library ieee;
use ieee.std_logic_1164.all;

-- A testbench has no ports

entity adder_tb is
end adder_tb;

architecture behav of adder_tb is
	-- Declaration of the component that will be instantiated
	component adder
		port (i0, i1 : in bit; ci : in bit; s : out bit; co : out bit);
	end component;
	
	-- Specifies which entity is bound with the component
	for adder_0: adder use entity work.adder;
	signal i0, i1, ci, s, co : bit;
begin
	-- Component instantiation
	adder_0: adder port map (i0 => i0, i1 => i1, ci => ci, s => s, co => co);
	
	-- This process does the real job
	process
		type pattern_type is record
		-- The inputs of the adder
		i0, i1, ci : bit;
		-- The expected outputs of the adder
		s, co : bit;
	end record;
	-- The patterns to apply
	type pattern_array is array (natural range <>) of pattern_type;
	constant patterns : pattern_array :=
	   (('0', '0', '0', '0', '0'),
		('0', '0', '1', '1', '0'),
		('0', '1', '0', '1', '0'),
		('0', '1', '1', '0', '1'),
		('1', '0', '0', '1', '0'),
		('1', '0', '1', '0', '1'),
		('1', '1', '0', '0', '1'),
		('1', '1', '1', '1', '1'));
	begin
		-- Check each pattern
		for i in patterns'range loop
			--Set the inputs
			i0 <= patterns(i).i0;
			i1 <= patterns(i).i1;
			ci <= patterns(i).ci;
			-- Wait for the results
			wait for 1 ns;
			-- Check the outputs
			assert s = patterns(i).s
				report "bad sum value" severity error;
			assert co = patterns(i).co
				report "bad carry out value" severity error;
		end loop;
		assert false report "end of test" severity note;
		-- Wait forever; this will finish the simulation
		wait;
	end process;
end behav;

GitHub Examples/Adder/adder.vcd
$date
  Wed Sep 16 22:19:48 2020
$end
$version
  GHDL v0
$end
$timescale
  1 fs
$end
$scope module standard $end
$upscope $end
$scope module std_logic_1164 $end
$upscope $end
$scope module adder_tb $end
$var reg 1 ! i0 $end
$var reg 1 " i1 $end
$var reg 1 # ci $end
$var reg 1 $ s $end
$var reg 1 % co $end
$scope module adder_0 $end
$var reg 1 & i0 $end
$var reg 1 ' i1 $end
$var reg 1 ( ci $end
$var reg 1 ) s $end
$var reg 1 * co $end
$upscope $end
$upscope $end
$enddefinitions $end
#0
0!
0"
0#
0$
0%
0&
0'
0(
0)
0*
#1000000
1#
1$
1(
1)
#2000000
1"
0#
1'
0(
#3000000
1#
0$
1%
1(
0)
1*
#4000000
1!
0"
0#
1$
0%
1&
0'
0(
1)
0*
#5000000
1#
0$
1%
1(
0)
1*
#6000000
1"
0#
1'
0(
#7000000
1#
1$
1(
1)
